game_asset_library/__init__.py
game_asset_library/animation.py
game_asset_library/asset_manager.py
game_asset_library/asset_templates.py
game_asset_library/audio_tools.py
game_asset_library/collision.py
game_asset_library/customization.py
game_asset_library/pygame_integration.py
game_asset_library/scene_manager.py
game_asset_library-1.0.1.dist-info/LICENSE
game_asset_library-1.0.1.dist-info/METADATA
game_asset_library-1.0.1.dist-info/WHEEL
game_asset_library-1.0.1.dist-info/top_level.txt
game_asset_library-1.0.1.dist-info/RECORD
