Metadata-Version: 2.1
Name: game-asset-library
Version: 1.0.1
Summary: A fully-featured game asset library for Pygame with customizable assets, animations, and more.
Home-page: https://github.com/yourgithubusername/game_asset_library
Author: Oscar Vaks
Author-email: oscar.vaks2010@gmail.com
Classifier: Programming Language :: Python :: 3
Classifier: License :: OSI Approved :: MIT License
Classifier: Operating System :: OS Independent
Requires-Python: >=3.6
License-File: LICENSE
Requires-Dist: pygame>=2.0.0
Requires-Dist: numpy>=1.21.0
